libusb/__about__.py
libusb/__config__.py
libusb/__init__.py
libusb/_config.py
libusb/_dll.py
libusb/_libusb.py
libusb/libusb.cfg
libusb/_platform/__init__.py
libusb/_platform/_limits.py
libusb/_platform/_platform.py
libusb/_platform/_linux/__init__.py
libusb/_platform/_linux/aarch64/libusb-1.0.so
libusb/_platform/_linux/x64/libusb-1.0.so
libusb/_platform/_linux/x86/libusb-1.0.so
libusb/_platform/_macos/__init__.py
libusb/_platform/_macos/x64/10.7/libusb-1.0.0.dylib
libusb/_platform/_macos/x64/11.6/libusb-1.0.0.dylib
libusb/_platform/_macos/x86/.keep
libusb/_platform/_windows/__init__.py
libusb/_platform/_windows/_win32.py
libusb/_platform/_windows/x64/libusb-1.0.def
libusb/_platform/_windows/x64/libusb-1.0.dll
libusb/_platform/_windows/x86/libusb-1.0.def
libusb/_platform/_windows/x86/libusb-1.0.dll
libusb-1.0.29.dist-info/licenses/LICENSE
libusb-1.0.29.dist-info/METADATA
libusb-1.0.29.dist-info/WHEEL
libusb-1.0.29.dist-info/top_level.txt
libusb-1.0.29.dist-info/RECORD
